AutomationService/__init__.py
AutomationService/__main__.py
AutomationService/api.py
AutomationService/const.py
AutomationService/service.py
pih_auto-1.11.dist-info/METADATA
pih_auto-1.11.dist-info/WHEEL
pih_auto-1.11.dist-info/entry_points.txt
pih_auto-1.11.dist-info/top_level.txt
pih_auto-1.11.dist-info/RECORD
